apitist/__init__.py
apitist/apitist.py
apitist/constructor.py
apitist/hooks.py
apitist/logging.py
apitist/random.py
apitist/requests.py
apitist/utils.py
python_apitist-0.5.2.dist-info/AUTHORS.rst
python_apitist-0.5.2.dist-info/LICENSE.txt
python_apitist-0.5.2.dist-info/METADATA
python_apitist-0.5.2.dist-info/WHEEL
python_apitist-0.5.2.dist-info/top_level.txt
python_apitist-0.5.2.dist-info/RECORD
