Metadata-Version: 2.1
Name: python-apitist
Version: 0.5.2
Summary: Brand new way to test your API
Home-page: https://github.com/zeburek/python-apitist
Author: Parviz Khavari
Author-email: csctclan@gmail.com
License: gpl3
Platform: any
Classifier: Development Status :: 4 - Beta
Classifier: Intended Audience :: Developers
Classifier: License :: OSI Approved :: GNU General Public License v3 (GPLv3)
Classifier: Programming Language :: Python
Classifier: Programming Language :: Python :: 3.6
Classifier: Programming Language :: Python :: 3.7
Classifier: Programming Language :: Python :: 3.8
Classifier: Topic :: Software Development :: Quality Assurance
Classifier: Topic :: Software Development :: Testing
Classifier: Typing :: Typed
Requires-Python: >=3.6
Requires-Dist: attrs (>=19.3.0)
Requires-Dist: cattrs-3.8 (>=0.9.1)
Requires-Dist: pendulum (>=2.0.5)
Requires-Dist: requests (>=2.22.0)
Provides-Extra: testing
Requires-Dist: pytest ; extra == 'testing'
Requires-Dist: pytest-cov ; extra == 'testing'
Requires-Dist: testfixtures ; extra == 'testing'
